riskgpt/__init__.py
riskgpt/api.py
riskgpt/logger.py
riskgpt/py.typed
riskgpt/chains/__init__.py
riskgpt/chains/base.py
riskgpt/chains/challenge_questions.py
riskgpt/chains/challenge_risk.py
riskgpt/chains/challenge_risks.py
riskgpt/chains/check_bias.py
riskgpt/chains/check_definition.py
riskgpt/chains/communicate_risks.py
riskgpt/chains/correlation_tags.py
riskgpt/chains/cost_benefit.py
riskgpt/chains/keypoint_text.py
riskgpt/chains/opportunities.py
riskgpt/chains/risk_assessment.py
riskgpt/chains/risk_categories.py
riskgpt/chains/risk_drivers.py
riskgpt/chains/risk_identification.py
riskgpt/chains/risk_indicators.py
riskgpt/chains/risk_mitigations.py
riskgpt/config/__init__.py
riskgpt/config/memory.py
riskgpt/config/settings.py
riskgpt/helpers/__init__.py
riskgpt/helpers/circuit_breaker.py
riskgpt/helpers/extraction.py
riskgpt/helpers/memory_factory.py
riskgpt/helpers/misc.py
riskgpt/helpers/prompt_loader.py
riskgpt/helpers/search.py
riskgpt/models/__init__.py
riskgpt/models/base.py
riskgpt/models/common.py
riskgpt/models/enums.py
riskgpt/models/chains/__init__.py
riskgpt/models/chains/assessment.py
riskgpt/models/chains/bias_check.py
riskgpt/models/chains/categorization.py
riskgpt/models/chains/communication.py
riskgpt/models/chains/correlation.py
riskgpt/models/chains/definition_check.py
riskgpt/models/chains/drivers.py
riskgpt/models/chains/mitigation.py
riskgpt/models/chains/monitoring.py
riskgpt/models/chains/opportunity.py
riskgpt/models/chains/questions.py
riskgpt/models/chains/risk.py
riskgpt/models/utils/__init__.py
riskgpt/models/utils/search.py
riskgpt/models/workflows/__init__.py
riskgpt/models/workflows/analyse_risks.py
riskgpt/models/workflows/context.py
riskgpt/models/workflows/presentation.py
riskgpt/processors/__init__.py
riskgpt/processors/input_validator.py
riskgpt/prompts/__init__.py
riskgpt/workflows/__init__.py
riskgpt/workflows/enrich_context.py
riskgpt/workflows/prepare_presentation_output.py
riskgpt/workflows/risk_workflow.py
riskgpt-0.2.0.dist-info/licenses/LICENSE
riskgpt-0.2.0.dist-info/METADATA
riskgpt-0.2.0.dist-info/WHEEL
riskgpt-0.2.0.dist-info/top_level.txt
riskgpt-0.2.0.dist-info/RECORD
