Metadata-Version: 2.4
Name: riskgpt
Version: 0.2.0
Summary: Analyze project risks and opportunities using AI
Author-email: Thomas Wolter <thwolter@gmail.com>
License-Expression: MIT
Project-URL: Documentation, https://thwolter.github.io/riskgpt/
Project-URL: Source, https://github.com/thwolter/riskgpt.git
Project-URL: Tracker, https://github.com/thwolter/riskgpt/issues
Classifier: Development Status :: 4 - Beta
Classifier: Intended Audience :: Developers
Classifier: Programming Language :: Python :: 3
Classifier: Programming Language :: Python :: 3.12
Classifier: Topic :: Software Development :: Libraries :: Python Modules
Requires-Python: >=3.12
License-File: LICENSE
Requires-Dist: duckduckgo-search>=8.0.4
Requires-Dist: google-api-python-client>=2.173.0
Requires-Dist: langchain>=0.3.26
Requires-Dist: pybreaker>=1.3.0
Requires-Dist: pydantic>=2.11.7
Requires-Dist: pydantic-settings>=2.10.0
Requires-Dist: wikipedia>=1.4.0
Requires-Dist: langchain-community>=0.3.26
Requires-Dist: langchain-openai>=0.3.25
Requires-Dist: langgraph>=0.4.8
Requires-Dist: langchain-google-community>=2.0.7
Requires-Dist: redis>=6.2.0
Requires-Dist: langchain-tavily>=0.2.4
Dynamic: license-file
